baec/__init__.py
baec/_version.py
baec/coordinates.py
baec/project.py
baec/measurements/__init__.py
baec/measurements/measured_settlement.py
baec/measurements/measured_settlement_series.py
baec/measurements/measurement_device.py
baec/measurements/plot_utils.py
baec/measurements/settlement_rod_measurement.py
baec/measurements/settlement_rod_measurement_series.py
baec/measurements/io/__init__.py
baec/measurements/io/basetime.py
baec/measurements/io/zbase.py
baec/model/__init__.py
baec/model/fitcore.py
baec-0.2.2.dist-info/licenses/LICENSE
baec-0.2.2.dist-info/METADATA
baec-0.2.2.dist-info/WHEEL
baec-0.2.2.dist-info/top_level.txt
baec-0.2.2.dist-info/RECORD
