Metadata-Version: 2.4
Name: baec
Version: 0.2.2
Summary: Python SDK to create Model Generators and add them into the BAEC platform.
License: MIT License
Project-URL: repository, https://github.com/cemsbv/BAEC
Keywords: API,BAEC,CEMS,CRUX
Requires-Python: >=3.9
License-File: LICENSE
Requires-Dist: numpy<3,>2
Requires-Dist: pandas<3,>2
Requires-Dist: cems-nuclei[client]<4,>=0.5
Requires-Dist: matplotlib<4,>=3.8
Requires-Dist: tqdm[notebook]<5,>4
Requires-Dist: pyproj<4,>3
Provides-Extra: test
Requires-Dist: coveralls; extra == "test"
Requires-Dist: pytest; extra == "test"
Requires-Dist: requests-mock; extra == "test"
Provides-Extra: docs
Requires-Dist: Sphinx==6.1.3; extra == "docs"
Requires-Dist: sphinx-autodoc-typehints==1.22; extra == "docs"
Requires-Dist: ipython==8.11.0; extra == "docs"
Requires-Dist: asteroid-sphinx-theme==0.0.3; extra == "docs"
Requires-Dist: sphinx_rtd_theme<2,>1.2; extra == "docs"
Requires-Dist: enum-tools[sphinx]<0.14,>=0.13; extra == "docs"
Provides-Extra: aws
Requires-Dist: boto3<2,>1.34; extra == "aws"
Provides-Extra: gui
Requires-Dist: marimo[recommended]<0.15,>0.14; extra == "gui"
Requires-Dist: micropip<0.11,>0.10; extra == "gui"
Dynamic: license-file
